casper_r2sdf_fft/__init__.py
casper_r2sdf_fft-0.0.6.dist-info/METADATA
casper_r2sdf_fft-0.0.6.dist-info/WHEEL
casper_r2sdf_fft-0.0.6.dist-info/licenses/LICENSE
casper_r2sdf_fft-0.0.6.dist-info/RECORD
